remove_overlap/__init__.py
remove_overlap/chan.py
remove_overlap/decompose.py
remove_overlap/test.py
remove_overlap/model/edge.py
remove_overlap/model/event.py
remove_overlap/model/event_pool.py
remove_overlap/model/event_type.py
remove_overlap/model/hrectangle.py
remove_overlap/utils/cut_bounding_box.py
remove_overlap/utils/overlap.py
remove_overlap/utils/plot.py
remove_overlap/utils/print.py
remove_overlap/utils/split_boxes.py
remove_overlap-0.0.4.dist-info/LICENSE
remove_overlap-0.0.4.dist-info/METADATA
remove_overlap-0.0.4.dist-info/WHEEL
remove_overlap-0.0.4.dist-info/top_level.txt
remove_overlap-0.0.4.dist-info/RECORD
