Metadata-Version: 2.1
Name: remove_overlap
Version: 0.0.4
Summary: Decompose hyperrectangles in d space
Author-email: Assem Hebik <assimhabe@gmail.com>
Project-URL: Homepage, https://github.com/assimhabeek/remove-overlap
Project-URL: Issues, https://github.com/assimhabeek/remove-overlap/issues
Classifier: Programming Language :: Python :: 3
Classifier: License :: OSI Approved :: MIT License
Classifier: Operating System :: OS Independent
Requires-Python: >=3.8
License-File: LICENSE
